{
  "version": "2.8.13",
  "notes": "{\"changes\":[{\"description\":\"chore: bump reqwest from 0.12.28 to 0.13.1 backend-deps group\",\"contributor\":\"dependabot[bot]\",\"pullRequestUrl\":\"https://github.com/open-goal/launcher/pull/901\"},{\"description\":\"chore: bump the frontend-deps group with 4 updates\",\"contributor\":\"dependabot[bot]\",\"pullRequestUrl\":\"https://github.com/open-goal/launcher/pull/893\"},{\"description\":\"chore: bump actions/upload-artifact from 5 to 6\",\"contributor\":\"dependabot[bot]\",\"pullRequestUrl\":\"https://github.com/open-goal/launcher/pull/900\"},{\"description\":\"versions: don't leave behind an empty folder if the download fails\",\"contributor\":\"xTVaser\",\"pullRequestUrl\":\"https://github.com/open-goal/launcher/pull/902\"},{\"description\":\"Separate mods install progress components\",\"contributor\":\"trippjoe\",\"pullRequestUrl\":\"https://github.com/open-goal/launcher/pull/908\"},{\"description\":\"Fix: \\\"An unexpected error occurred\\\" associated with outdated vcc runtime\",\"contributor\":\"trippjoe\",\"pullRequestUrl\":\"https://github.com/open-goal/launcher/pull/909\"},{\"description\":\"Link to mod website, when available\",\"contributor\":\"dallmeyer\",\"pullRequestUrl\":\"https://github.com/open-goal/launcher/pull/910\"},{\"description\":\"DRY: Collect repeated requirements checking code into a single store.\",\"contributor\":\"trippjoe\",\"pullRequestUrl\":\"https://github.com/open-goal/launcher/pull/911\"},{\"description\":\"DRY: Let the router do the routing\",\"contributor\":\"trippjoe\",\"pullRequestUrl\":\"https://github.com/open-goal/launcher/pull/912\"},{\"description\":\"FIX: Notify users that the game settings have been reset\",\"contributor\":\"trippjoe\",\"pullRequestUrl\":\"https://github.com/open-goal/launcher/pull/913\"},{\"description\":\"Reduce unneeded log spam\",\"contributor\":\"trippjoe\",\"pullRequestUrl\":\"https://github.com/open-goal/launcher/pull/914\"},{\"description\":\"Refactor vcc runtime detection\",\"contributor\":\"trippjoe\",\"pullRequestUrl\":\"https://github.com/open-goal/launcher/pull/921\"},{\"description\":\"Refactor util/tar functions\",\"contributor\":\"trippjoe\",\"pullRequestUrl\":\"https://github.com/open-goal/launcher/pull/922\"},{\"description\":\"remove redundant util function\",\"contributor\":\"trippjoe\",\"pullRequestUrl\":\"https://github.com/open-goal/launcher/pull/923\"},{\"description\":\"Refactor util/file.rs\",\"contributor\":\"trippjoe\",\"pullRequestUrl\":\"https://github.com/open-goal/launcher/pull/924\"},{\"description\":\"Refactor util/network.rs\",\"contributor\":\"trippjoe\",\"pullRequestUrl\":\"https://github.com/open-goal/launcher/pull/925\"},{\"description\":\"Refactor util/game_tests.rs\",\"contributor\":\"trippjoe\",\"pullRequestUrl\":\"https://github.com/open-goal/launcher/pull/926\"},{\"description\":\"Refactor util/process.rs\",\"contributor\":\"trippjoe\",\"pullRequestUrl\":\"https://github.com/open-goal/launcher/pull/927\"},{\"description\":\"Refactor features/mods\",\"contributor\":\"trippjoe\",\"pullRequestUrl\":\"https://github.com/open-goal/launcher/pull/928\"},{\"description\":\"Refactor fn download_file\",\"contributor\":\"trippjoe\",\"pullRequestUrl\":\"https://github.com/open-goal/launcher/pull/929\"},{\"description\":\"Refactor/commands util\",\"contributor\":\"trippjoe\",\"pullRequestUrl\":\"https://github.com/open-goal/launcher/pull/930\"},{\"description\":\"Module restructuring\",\"contributor\":\"trippjoe\",\"pullRequestUrl\":\"https://github.com/open-goal/launcher/pull/931\"},{\"description\":\"Refactor: commands/game.rs\",\"contributor\":\"trippjoe\",\"pullRequestUrl\":\"https://github.com/open-goal/launcher/pull/932\"},{\"description\":\"Refactor commands/versions.rs\",\"contributor\":\"trippjoe\",\"pullRequestUrl\":\"https://github.com/open-goal/launcher/pull/933\"},{\"description\":\"refactor download_version\",\"contributor\":\"trippjoe\",\"pullRequestUrl\":\"https://github.com/open-goal/launcher/pull/934\"},{\"description\":\"fix: bypass requirements\",\"contributor\":\"trippjoe\",\"pullRequestUrl\":\"https://github.com/open-goal/launcher/pull/935\"},{\"description\":\"fix: prevent game controls dropdown from going off screen\",\"contributor\":\"trippjoe\",\"pullRequestUrl\":\"https://github.com/open-goal/launcher/pull/938\"},{\"description\":\"fix startup routing issue\",\"contributor\":\"trippjoe\",\"pullRequestUrl\":\"https://github.com/open-goal/launcher/pull/937\"},{\"description\":\"Refactor binaries.rs, texture_packs.rs, toast\",\"contributor\":\"trippjoe\",\"pullRequestUrl\":\"https://github.com/open-goal/launcher/pull/936\"},{\"description\":\"fix: getActiveVersion\",\"contributor\":\"trippjoe\",\"pullRequestUrl\":\"https://github.com/open-goal/launcher/pull/939\"},{\"description\":\"Omit installed_vcc_runtime from support_info.json if not windows\",\"contributor\":\"trippjoe\",\"pullRequestUrl\":\"https://github.com/open-goal/launcher/pull/940\"},{\"description\":\"use minimumSystemVersion config to ensure macos >= 15\",\"contributor\":\"trippjoe\",\"pullRequestUrl\":\"https://github.com/open-goal/launcher/pull/941\"},{\"description\":\"add: get the exit signal from extractor/decompiler/compiler\",\"contributor\":\"trippjoe\",\"pullRequestUrl\":\"https://github.com/open-goal/launcher/pull/942\"},{\"description\":\"chore: bump the backend-deps group across 1 directory with 15 updates\",\"contributor\":\"dependabot[bot]\",\"pullRequestUrl\":\"https://github.com/open-goal/launcher/pull/919\"},{\"description\":\"chore: bump the frontend-deps group across 1 directory with 18 updates\",\"contributor\":\"dependabot[bot]\",\"pullRequestUrl\":\"https://github.com/open-goal/launcher/pull/917\"},{\"description\":\"update dependabot to group front-end and back-end tauri updates together\",\"contributor\":\"trippjoe\",\"pullRequestUrl\":\"https://github.com/open-goal/launcher/pull/943\"},{\"description\":\"Bump the \\\"tauri\\\" group with 2 updates across multiple ecosystems\",\"contributor\":\"dependabot[bot]\",\"pullRequestUrl\":\"https://github.com/open-goal/launcher/pull/944\"},{\"description\":\"Misc warnings\",\"contributor\":\"trippjoe\",\"pullRequestUrl\":\"https://github.com/open-goal/launcher/pull/945\"},{\"description\":\"Refactor mods platform filtering\",\"contributor\":\"trippjoe\",\"pullRequestUrl\":\"https://github.com/open-goal/launcher/pull/946\"}]}",
  "pub_date": "2026-03-22T18:32:30.365Z",
  "platforms": {
    "darwin-aarch64": {
      "signature": "dW50cnVzdGVkIGNvbW1lbnQ6IHNpZ25hdHVyZSBmcm9tIHRhdXJpIHNlY3JldCBrZXkKUlVTU1FRci9NckROT1lOcld5ZGxUMUgraW9yamh1QWp5UXRSUnlmL0wwbzRJMFFORmNkNlc0N2pybG9pTzZOM2RkRnFZOTFqYkpFdWpNczJmUzZ0SDV0dUNkZVNhM0Q5ZkE4PQp0cnVzdGVkIGNvbW1lbnQ6IHRpbWVzdGFtcDoxNzc0MjAzNzMxCWZpbGU6T3BlbkdPQUwtTGF1bmNoZXIuYXBwLnRhci5negpXVUpMeSs4ZEdHNXRTTUxrdW1kWTFWb0VTZVJmbzBFQmRqelhKWDlDSDdVZUpSamp0d2kxdGkzeTJnVEx6YUFlRGJrNUVCb0FJWWRLam9UU2FmSzRDUT09Cg==",
      "url": "https://github.com/open-goal/launcher/releases/download/v2.8.13/OpenGOAL-Launcher_aarch64.app.tar.gz"
    },
    "darwin-aarch64-app": {
      "signature": "dW50cnVzdGVkIGNvbW1lbnQ6IHNpZ25hdHVyZSBmcm9tIHRhdXJpIHNlY3JldCBrZXkKUlVTU1FRci9NckROT1lOcld5ZGxUMUgraW9yamh1QWp5UXRSUnlmL0wwbzRJMFFORmNkNlc0N2pybG9pTzZOM2RkRnFZOTFqYkpFdWpNczJmUzZ0SDV0dUNkZVNhM0Q5ZkE4PQp0cnVzdGVkIGNvbW1lbnQ6IHRpbWVzdGFtcDoxNzc0MjAzNzMxCWZpbGU6T3BlbkdPQUwtTGF1bmNoZXIuYXBwLnRhci5negpXVUpMeSs4ZEdHNXRTTUxrdW1kWTFWb0VTZVJmbzBFQmRqelhKWDlDSDdVZUpSamp0d2kxdGkzeTJnVEx6YUFlRGJrNUVCb0FJWWRLam9UU2FmSzRDUT09Cg==",
      "url": "https://github.com/open-goal/launcher/releases/download/v2.8.13/OpenGOAL-Launcher_aarch64.app.tar.gz"
    },
    "linux-x86_64": {
      "signature": "dW50cnVzdGVkIGNvbW1lbnQ6IHNpZ25hdHVyZSBmcm9tIHRhdXJpIHNlY3JldCBrZXkKUlVTU1FRci9NckROT1R2WWVxQndmNTRpTTZRSVFYc1d4anpqdmU5bG0vbGRpYm0xTUpORDRxK1lqcUxZS3hhMm9LU3BYYUsxdDVySlZSb3BsQURhZ21UL3lXQjNNWUg3TkFzPQp0cnVzdGVkIGNvbW1lbnQ6IHRpbWVzdGFtcDoxNzc0MjAzOTQ1CWZpbGU6T3BlbkdPQUwtTGF1bmNoZXJfMi44LjEzX2FtZDY0LkFwcEltYWdlLnRhci5negpXM3NONDlVODV1NDRWbkcrdXhPMEluK3Rzb2lQWENodDlLM3lWdHZhdFJYT0YwSGQ0QVo0MW9ZK0VqQzlLMXVyRW9yMlM2T2syUDQwdEFDR0JkN1BEdz09Cg==",
      "url": "https://github.com/open-goal/launcher/releases/download/v2.8.13/OpenGOAL-Launcher_2.8.13_amd64.AppImage.tar.gz"
    },
    "linux-x86_64-appimage": {
      "signature": "dW50cnVzdGVkIGNvbW1lbnQ6IHNpZ25hdHVyZSBmcm9tIHRhdXJpIHNlY3JldCBrZXkKUlVTU1FRci9NckROT2FlNy9uOCtOUHZ4RE9yOVdyTDdDbHJXVDdnSkR1a3JZVHFUWTBVa1ArVW5QcHM4U0ZpSmJ0NitKN3BLcWx6RE8ra1FIS3g3b0JhU29FdGZRUnljc3dvPQp0cnVzdGVkIGNvbW1lbnQ6IHRpbWVzdGFtcDoxNzc0MjAzOTQ1CWZpbGU6T3BlbkdPQUwtTGF1bmNoZXJfMi44LjEzX2FtZDY0LkFwcEltYWdlCjVSVU9qdVV1NStZQ0kxekVuaURaVHRUL3NaNUw2L3l5VE5zVzJPVU8zNWxvZmtQUzNBWDFDelc2S2FjUDlCK3g1M2xMK1V4dXQ4a3BCV3NaL0xwL0NRPT0K",
      "url": "https://github.com/open-goal/launcher/releases/download/v2.8.13/OpenGOAL-Launcher_2.8.13_amd64.AppImage"
    },
    "linux-x86_64-deb": {
      "signature": "dW50cnVzdGVkIGNvbW1lbnQ6IHNpZ25hdHVyZSBmcm9tIHRhdXJpIHNlY3JldCBrZXkKUlVTU1FRci9NckROT1dJVXJOSHdsUHJLTjhvS1dhVW0xdWQ1TVhPUldaTlFYUXpYajJZQ3Z4em9MRE9HNk5YY2ZjeitncjRFTmRIR3huaXg3cm4rT2laVGVIM3FINTlCR1F3PQp0cnVzdGVkIGNvbW1lbnQ6IHRpbWVzdGFtcDoxNzc0MjAzOTQ1CWZpbGU6T3BlbkdPQUwtTGF1bmNoZXJfMi44LjEzX2FtZDY0LmRlYgp3cXRsYkQ2UjFRWkExYUlTRUMzU1Jvc2Jhc1NaSkdGanNBb0thK0ZRZGV4U0JuNjlKd2gxckV6Y1paaDhCdFQ5OTlxUWNNRE9Na3dIRzZ6TEhZTUlEZz09Cg==",
      "url": "https://github.com/open-goal/launcher/releases/download/v2.8.13/OpenGOAL-Launcher_2.8.13_amd64.deb"
    },
    "windows-x86_64": {
      "signature": "dW50cnVzdGVkIGNvbW1lbnQ6IHNpZ25hdHVyZSBmcm9tIHRhdXJpIHNlY3JldCBrZXkKUlVTU1FRci9NckROT2JNdW9lVkkwdC9pb0daZEFTcnRMYm9TdkppMUdpSjIzbFFuMHEyQWZoTEVFVU5OaXJ1ZUxLQVFLQjVEbVBWNEZnWnhGbFpjMDZ2TXJxSXJFQVZLMXdzPQp0cnVzdGVkIGNvbW1lbnQ6IHRpbWVzdGFtcDoxNzc0MjA0MDM1CWZpbGU6T3BlbkdPQUwtTGF1bmNoZXJfMi44LjEzX3g2NF9lbi1VUy5tc2kuemlwCkRjaVo3L040QkVhaFJuMUhEY2llTnp5VUp3MVlpT0JkaEI4b1JpZWxVVER2Z2NGWnc0RlU1ZnpRWnp4VFdpVWF1Sm1ZMGhWakZ6d1EzbzZoSnF2TUNRPT0K",
      "url": "https://github.com/open-goal/launcher/releases/download/v2.8.13/OpenGOAL-Launcher_2.8.13_x64_en-US.msi.zip"
    },
    "windows-x86_64-msi": {
      "signature": "dW50cnVzdGVkIGNvbW1lbnQ6IHNpZ25hdHVyZSBmcm9tIHRhdXJpIHNlY3JldCBrZXkKUlVTU1FRci9NckROT2V4eWEvZVc5MUU3anNBZEoyTXNzOFdIT1JQaGZqbVU5NklQWjNYOE83RUFsZHI1Y1NsNW5iTFZOZDhaQXVhVThxcXkzeHc3MG1pcFMzcDJza3g4R3dRPQp0cnVzdGVkIGNvbW1lbnQ6IHRpbWVzdGFtcDoxNzc0MjA0MDM0CWZpbGU6T3BlbkdPQUwtTGF1bmNoZXJfMi44LjEzX3g2NF9lbi1VUy5tc2kKWUZIRC9VME5wNi9JK0RXU3h2VXgyZTcwUkVGeUpXU3BLZ1hCLzJKLzlGZU9PZGh0ak9tTXFPVm9YY25zSzBNQlRITTNPNkNVMWlyVnBya29xZXZpREE9PQo=",
      "url": "https://github.com/open-goal/launcher/releases/download/v2.8.13/OpenGOAL-Launcher_2.8.13_x64_en-US.msi"
    },
    "darwin-x86_64": {
      "signature": "dW50cnVzdGVkIGNvbW1lbnQ6IHNpZ25hdHVyZSBmcm9tIHRhdXJpIHNlY3JldCBrZXkKUlVTU1FRci9NckROT1ROdWY2bEc0QTJTeDdEdnRneTNDVFYrQW9Scm5tTGI5NzhDa052K3l1WlpmK0tST3NxTGpIbjVhWmhmOVdkNmRpMW5Qb3diaHc5MDc4SU9PeTkvZEFNPQp0cnVzdGVkIGNvbW1lbnQ6IHRpbWVzdGFtcDoxNzc0MjA0MzQ0CWZpbGU6T3BlbkdPQUwtTGF1bmNoZXIuYXBwLnRhci5negpmaGR6ZDhVd21WMXJDL2U4VWM0RnFJTGl2K1E4bWhoYVBXRTFBTXpIME5sYWkreG9mbVhTcmRKY3orUFZBQm5NOGZ6WVB6RndteWFTUjhlR29pTDFCZz09Cg==",
      "url": "https://github.com/open-goal/launcher/releases/download/v2.8.13/OpenGOAL-Launcher_x64.app.tar.gz"
    },
    "darwin-x86_64-app": {
      "signature": "dW50cnVzdGVkIGNvbW1lbnQ6IHNpZ25hdHVyZSBmcm9tIHRhdXJpIHNlY3JldCBrZXkKUlVTU1FRci9NckROT1ROdWY2bEc0QTJTeDdEdnRneTNDVFYrQW9Scm5tTGI5NzhDa052K3l1WlpmK0tST3NxTGpIbjVhWmhmOVdkNmRpMW5Qb3diaHc5MDc4SU9PeTkvZEFNPQp0cnVzdGVkIGNvbW1lbnQ6IHRpbWVzdGFtcDoxNzc0MjA0MzQ0CWZpbGU6T3BlbkdPQUwtTGF1bmNoZXIuYXBwLnRhci5negpmaGR6ZDhVd21WMXJDL2U4VWM0RnFJTGl2K1E4bWhoYVBXRTFBTXpIME5sYWkreG9mbVhTcmRKY3orUFZBQm5NOGZ6WVB6RndteWFTUjhlR29pTDFCZz09Cg==",
      "url": "https://github.com/open-goal/launcher/releases/download/v2.8.13/OpenGOAL-Launcher_x64.app.tar.gz"
    }
  }
}
